cubic_interpolate/__init__.py
cubic_interpolate/interpolation.py
cubic_interpolate-0.1.2.dist-info/LICENSE
cubic_interpolate-0.1.2.dist-info/METADATA
cubic_interpolate-0.1.2.dist-info/WHEEL
cubic_interpolate-0.1.2.dist-info/top_level.txt
cubic_interpolate-0.1.2.dist-info/RECORD
