Metadata-Version: 2.1
Name: cubic-interpolate
Version: 0.1.2
Summary: Find the cubic interpolation for a given data
Home-page: UNKNOWN
Author: Kenan Kassab
Author-email: kenankassab1997@gmail.com
License: UNKNOWN
Platform: UNKNOWN
Classifier: Programming Language :: Python :: 3
Classifier: License :: OSI Approved :: MIT License
Classifier: Operating System :: OS Independent
Requires-Python: >=3.7
License-File: LICENSE
